.coveragerc
.editorconfig
.gitignore
.travis.yml
LICENSE
README.md
pyproject.toml
requirements.txt
requirements_dev.txt
setup.cfg
setup.py
.github/workflows/python-publish.yml
democritus_file_system/__init__.py
democritus_file_system/atomic_writes.py
democritus_file_system/directories.py
democritus_file_system/directories_temp_utils.py
democritus_file_system/files.py
democritus_file_system/files_temp_utils.py
democritus_file_system.egg-info/PKG-INFO
democritus_file_system.egg-info/SOURCES.txt
democritus_file_system.egg-info/dependency_links.txt
democritus_file_system.egg-info/requires.txt
democritus_file_system.egg-info/top_level.txt
democritus_file_system.egg-info/zip-safe
tests/__init__.py
tests/test_atomic_writes.py
tests/test_directories.py
tests/test_files.py